bert_multitask_server-0.1.2.data/scripts/bert-multitask-serving-start
bert_multitask_serving/__init__.py
bert_multitask_serving/server/__init__.py
bert_multitask_serving/server/helper.py
bert_multitask_serving/server/result_parser.py
bert_multitask_serving/server/zmq_decor.py
bert_multitask_serving/server/bert/__init__.py
bert_multitask_serving/server/bert/extract_features.py
bert_multitask_serving/server/bert/tokenization.py
bert_multitask_server-0.1.2.dist-info/METADATA
bert_multitask_server-0.1.2.dist-info/WHEEL
bert_multitask_server-0.1.2.dist-info/top_level.txt
bert_multitask_server-0.1.2.dist-info/RECORD
