Metadata-Version: 2.1
Name: bert-multitask-server
Version: 0.1.2
Summary: A service to serve bert_multitask_learning models(server)
Home-page: https://github.com/JayYip/bert-multitask-service
Author: Jay Yip
Author-email: junpang.yip@gmail.com
License: MIT
Keywords: bert nlp tensorflow machine learning sentence encoding embedding serving
Platform: UNKNOWN
Classifier: Programming Language :: Python :: 3.6
Classifier: License :: OSI Approved :: MIT License
Classifier: Operating System :: OS Independent
Classifier: Topic :: Scientific/Engineering :: Artificial Intelligence
Requires-Dist: setuptools (==40.5.0)
Requires-Dist: tqdm (==4.28.1)
Requires-Dist: six (==1.11.0)
Requires-Dist: tensorflow-gpu (>=1.12.0)
Requires-Dist: numpy (==1.15.4)
Requires-Dist: tensor2tensor (==1.11.0)
Requires-Dist: termcolor (==1.1.0)
Requires-Dist: GPUtil (==1.4.0)
Requires-Dist: protobuf (==3.6.1)
Requires-Dist: scikit-learn (==0.20.2)
Requires-Dist: pyzmq (==17.1.2)
